Moonlight/__init__.py
MoonlightDB-2.0.2.dist-info/LICENSE
MoonlightDB-2.0.2.dist-info/METADATA
MoonlightDB-2.0.2.dist-info/WHEEL
MoonlightDB-2.0.2.dist-info/entry_points.txt
MoonlightDB-2.0.2.dist-info/top_level.txt
MoonlightDB-2.0.2.dist-info/RECORD
