Metadata-Version: 2.1
Name: MoonlightDB
Version: 2.0.2
Summary: Moonlight is a lightweight JSON-database for Python.
Home-page: https://github.com/De4oult/Moonlight
Author: de4oult
Author-email: kayra.dist@gmail.com
License: MIT License
Keywords: python,cli,package,json,database,web,interface,async,python3,python3.12,database-management,moonlight
Requires-Python: >=3.12
License-File: LICENSE
Requires-Dist: filelock
Requires-Dist: sanic
Requires-Dist: sanic-cors
Requires-Dist: click
Requires-Dist: pick
Requires-Dist: InquirerPy
Requires-Dist: rich
Requires-Dist: loguru
Requires-Dist: markdown
Requires-Dist: aiofiles
